Algorithms/LinearRegression.py
Algorithms/LogisticRegression.py
Algorithms/SVM.py
Algorithms/__init__.py
Algorithms/mymodule.py
vasanth-0.1.dist-info/LICENSE
vasanth-0.1.dist-info/METADATA
vasanth-0.1.dist-info/WHEEL
vasanth-0.1.dist-info/top_level.txt
vasanth-0.1.dist-info/RECORD
