Metadata-Version: 2.1
Name: vasanth
Version: 0.1
Summary: A simple module that provides math functions and machine learning algorithms
Author: Vasantha Raj
Author-email: vasanthraj679@gmail.com
Classifier: Programming Language :: Python :: 3
Classifier: License :: OSI Approved :: MIT License
Classifier: Operating System :: OS Independent
Requires-Python: >=3.6
License-File: LICENSE
